syntax_diagrams/__init__.py
syntax_diagrams/_version.py
syntax_diagrams/element.py
syntax_diagrams/measure.py
syntax_diagrams/py.typed
syntax_diagrams/render.py
syntax_diagrams/resolver.py
syntax_diagrams/_impl/__init__.py
syntax_diagrams/_impl/load.py
syntax_diagrams/_impl/ridge_line.py
syntax_diagrams/_impl/vec.py
syntax_diagrams/_impl/render/__init__.py
syntax_diagrams/_impl/render/svg.py
syntax_diagrams/_impl/render/text.py
syntax_diagrams/_impl/tree/__init__.py
syntax_diagrams/_impl/tree/barrier.py
syntax_diagrams/_impl/tree/choice.py
syntax_diagrams/_impl/tree/end.py
syntax_diagrams/_impl/tree/group.py
syntax_diagrams/_impl/tree/node.py
syntax_diagrams/_impl/tree/one_or_more.py
syntax_diagrams/_impl/tree/sequence.py
syntax_diagrams/_impl/tree/skip.py
syntax_diagrams-1.0.0.post1.dist-info/licenses/LICENSE
syntax_diagrams-1.0.0.post1.dist-info/METADATA
syntax_diagrams-1.0.0.post1.dist-info/WHEEL
syntax_diagrams-1.0.0.post1.dist-info/top_level.txt
syntax_diagrams-1.0.0.post1.dist-info/RECORD
